missing_101883071/__init__.py
missing_101883071/missing_101883071.py
missing_101883071-1.0.1.dist-info/LICENSE
missing_101883071-1.0.1.dist-info/METADATA
missing_101883071-1.0.1.dist-info/WHEEL
missing_101883071-1.0.1.dist-info/entry_points.txt
missing_101883071-1.0.1.dist-info/top_level.txt
missing_101883071-1.0.1.dist-info/RECORD
